gsheets_helper.py
gsheets_helper-0.0.1.dist-info/LICENSE
gsheets_helper-0.0.1.dist-info/METADATA
gsheets_helper-0.0.1.dist-info/WHEEL
gsheets_helper-0.0.1.dist-info/top_level.txt
gsheets_helper-0.0.1.dist-info/RECORD
