Metadata-Version: 2.1
Name: gsheets-helper
Version: 0.0.1
Summary: Helper functions wrapper over the google sheets python api
Home-page: UNKNOWN
Author: Sunny DSouza
License: UNKNOWN
Platform: UNKNOWN
Classifier: Programming Language :: Python :: 3
Classifier: License :: OSI Approved :: MIT License
Classifier: Operating System :: OS Independent
Requires-Python: >=3.6
License-File: LICENSE
Requires-Dist: google-api-python-client
Requires-Dist: google-auth-httplib2
Requires-Dist: google-auth-oauthlib
Requires-Dist: pandas
